fathom_mcp/__init__.py
fathom_mcp/__main__.py
fathom_mcp/config.py
fathom_mcp/errors.py
fathom_mcp/lifecycle.py
fathom_mcp/logging_config.py
fathom_mcp/middleware.py
fathom_mcp/prompts.py
fathom_mcp/resources.py
fathom_mcp/security.py
fathom_mcp/server.py
fathom_mcp/transports.py
fathom_mcp/cli/__init__.py
fathom_mcp/cli/test_client.py
fathom_mcp/pdf/__init__.py
fathom_mcp/pdf/parallel.py
fathom_mcp/search/__init__.py
fathom_mcp/search/cache.py
fathom_mcp/search/filter_builder.py
fathom_mcp/search/index.py
fathom_mcp/search/ugrep.py
fathom_mcp/search/watcher.py
fathom_mcp/tools/__init__.py
fathom_mcp/tools/browse.py
fathom_mcp/tools/read.py
fathom_mcp/tools/search.py
fathom_mcp/tools/validation.py
fathom_mcp-0.2.0.dist-info/METADATA
fathom_mcp-0.2.0.dist-info/WHEEL
fathom_mcp-0.2.0.dist-info/entry_points.txt
fathom_mcp-0.2.0.dist-info/licenses/LICENSE
fathom_mcp-0.2.0.dist-info/RECORD
