Metadata-Version: 2.4
Name: fathom-mcp
Version: 0.2.0
Summary: File-first knowledge base MCP server with ugrep search
Project-URL: Homepage, https://github.com/RomanShnurov/fathom-mcp
Project-URL: Documentation, https://github.com/RomanShnurov/fathom-mcp#readme
Project-URL: Repository, https://github.com/RomanShnurov/fathom-mcp
Project-URL: Issues, https://github.com/RomanShnurov/fathom-mcp/issues
Author-email: Roman Shnurov <vegadeveil@gmail.com>
License: MIT
License-File: LICENSE
Keywords: ai,claude,knowledge-base,llm,mcp,model-context-protocol,pdf,search
Classifier: Development Status :: 4 - Beta
Classifier: Environment :: Console
Classifier: Intended Audience :: Developers
Classifier: License :: OSI Approved :: MIT License
Classifier: Operating System :: OS Independent
Classifier: Programming Language :: Python :: 3
Classifier: Programming Language :: Python :: 3.12
Classifier: Programming Language :: Python :: 3.13
Classifier: Topic :: Scientific/Engineering :: Artificial Intelligence
Classifier: Topic :: Text Processing :: Indexing
Requires-Python: >=3.12
Requires-Dist: httpx>=0.26.0
Requires-Dist: mcp>=1.0.0
Requires-Dist: pydantic-settings>=2.0
Requires-Dist: pydantic>=2.0
Requires-Dist: pypdf>=4.0
Requires-Dist: pyyaml>=6.0
Requires-Dist: starlette>=0.36.0
Requires-Dist: tenacity>=8.0
Requires-Dist: uvicorn>=0.27.0
Provides-Extra: dev
Requires-Dist: mypy>=1.0; extra == 'dev'
Requires-Dist: pre-commit>=3.0; extra == 'dev'
Requires-Dist: pytest-asyncio>=0.23; extra == 'dev'
Requires-Dist: pytest-benchmark>=4.0; extra == 'dev'
Requires-Dist: pytest-cov>=4.0; extra == 'dev'
Requires-Dist: pytest>=8.0; extra == 'dev'
Requires-Dist: python-docx>=1.0; extra == 'dev'
Requires-Dist: ruff>=0.1.0; extra == 'dev'
Requires-Dist: types-pyyaml>=6.0; extra == 'dev'
Provides-Extra: inspector
Requires-Dist: nest-asyncio>=1.6.0; extra == 'inspector'
Requires-Dist: streamlit>=1.31.0; extra == 'inspector'
